README.md
setup.py
galaxiumtools/_init__.py
galaxiumtools/minio_handler.py
galaxiumtools/mlflow_handler.py
galaxiumtools.egg-info/PKG-INFO
galaxiumtools.egg-info/SOURCES.txt
galaxiumtools.egg-info/dependency_links.txt
galaxiumtools.egg-info/requires.txt
galaxiumtools.egg-info/top_level.txt
tests/test_minio_handler.py
tests/test_mlflow_handler.py